greet/__init__.py
x_data_processing-0.1.dist-info/METADATA
x_data_processing-0.1.dist-info/WHEEL
x_data_processing-0.1.dist-info/top_level.txt
x_data_processing-0.1.dist-info/RECORD
