Metadata-Version: 2.1
Name: x-data-processing
Version: 0.1
Summary: X-data-processing is a package for data processing.
Home-page: https://github.com/cdevent/x-data-processing
Author: CoteDevent
Author-email: srwind18@gmail.com
